watroo/__init__.py
watroo/utils.py
watroo/wavelets.py
watroo-0.0.4.dist-info/LICENSE.rst
watroo-0.0.4.dist-info/METADATA
watroo-0.0.4.dist-info/WHEEL
watroo-0.0.4.dist-info/top_level.txt
watroo-0.0.4.dist-info/RECORD
