Metadata-Version: 2.1
Name: watroo
Version: 0.0.4
Summary: A trous wavelet transform and utilities
Author-email: Frederic Auchere <frederic.auchere@gmail.com>
Project-URL: Homepage, https://git.ias.u-psud.fr/fauchere/wavelets
Classifier: Programming Language :: Python :: 3
Classifier: License :: OSI Approved :: MIT License
Classifier: Operating System :: OS Independent
Requires-Python: >=3.8
License-File: LICENSE.rst
Requires-Dist: numpy >=1.20.3
Requires-Dist: opencv-python >=4.5.1
Requires-Dist: scipy >=1.7.2
Requires-Dist: numexpr >=2.8.1
Requires-Dist: tqdm >=4.64
